[{"Year":1990,"Electricity and heat producers":7625,"Other energy industries":977,"Industry":3959,"Transport":4595,"Residential":1832,"Commercial and public services":774,"Agriculture":398,"Fishing":18,"Final consumption not elsewhere specified":342},{"Year":1995,"Electricity and heat producers":8169,"Other energy industries":1071,"Industry":3943,"Transport":5018,"Residential":1848,"Commercial and public services":727,"Agriculture":402,"Fishing":18,"Final consumption not elsewhere specified":192},{"Year":2000,"Electricity and heat producers":9364,"Other energy industries":1186,"Industry":3882,"Transport":5757,"Residential":1827,"Commercial and public services":705,"Agriculture":340,"Fishing":19,"Final consumption not elsewhere specified":158},{"Year":2005,"Electricity and heat producers":10979,"Other energy industries":1395,"Industry":4945,"Transport":6473,"Residential":1898,"Commercial and public services":783,"Agriculture":397,"Fishing":24,"Final consumption not elsewhere specified":181},{"Year":2010,"Electricity and heat producers":12527,"Other energy industries":1634,"Industry":6102,"Transport":6992,"Residential":1886,"Commercial and public services":815,"Agriculture":394,"Fishing":22,"Final consumption not elsewhere specified":199},{"Year":2015,"Electricity and heat producers":13405,"Other energy industries":1653,"Industry":6361,"Transport":7702,"Residential":1850,"Commercial and public services":832,"Agriculture":413,"Fishing":20,"Final consumption not elsewhere specified":195}]